src/my_api_file.py
my_python_projcet-0.1.1a4.dist-info/METADATA
my_python_projcet-0.1.1a4.dist-info/WHEEL
my_python_projcet-0.1.1a4.dist-info/RECORD
